MANIFEST.in
README.rst
myql-cli.py
requirements.txt
setup.cfg
setup.py
myql_cli.egg-info/PKG-INFO
myql_cli.egg-info/SOURCES.txt
myql_cli.egg-info/dependency_links.txt
myql_cli.egg-info/requires.txt
myql_cli.egg-info/top_level.txt
utils/__init__.py
utils/template.py
utils/utils.py