Metadata-Version: 1.1
Name: myql-cli
Version: 0.2.3
Summary: Python Wrapper for the Yahoo ! Query Language
Home-page: https://github.com/josuebrunel/myql-cli
Author: Josue Kouka
Author-email: josuebrunel@gmail.com
License: MIT
Download-URL: https://github.com/josuebrunel/myql-cli/archive/0.2.3.tar.gz
Platform: Any
